geo_calcs/__init__.py
geo_calcs/geo_calcs.py
geo_calcs/utils.py
geo_calcs/calculations/__init__.py
geo_calcs/calculations/geochem.py
geo_calcs/calculations/geochron.py
geo_calcs/geo_chem/__init__.py
geo_calcs/geo_chem/geo_chem.py
geo_calcs/geo_chron/__init__.py
geo_calcs/geo_chron/geo_chron.py
geo_calcs/visualizations/__init__.py
geo_calcs-0.1.3.dist-info/AUTHORS.md
geo_calcs-0.1.3.dist-info/AUTHORS.rst
geo_calcs-0.1.3.dist-info/LICENSE
geo_calcs-0.1.3.dist-info/METADATA
geo_calcs-0.1.3.dist-info/WHEEL
geo_calcs-0.1.3.dist-info/top_level.txt
geo_calcs-0.1.3.dist-info/RECORD
