Metadata-Version: 2.1
Name: geo-calcs
Version: 0.1.3
Summary: A Python package for caclulations and visualizations in geological sciences.
Home-page: https://github.com/drew026/geo_calcs
Author: Drew Heasman
Author-email: heasman.drew@gmail.com
License: MIT license
Keywords: geo_calcs
Platform: UNKNOWN
Classifier: Development Status :: 2 - Pre-Alpha
Classifier: Intended Audience :: Developers
Classifier: License :: OSI Approved :: MIT License
Classifier: Natural Language :: English
Classifier: Programming Language :: Python :: 3
Classifier: Programming Language :: Python :: 3.6
Classifier: Programming Language :: Python :: 3.7
Classifier: Programming Language :: Python :: 3.8
Requires-Python: >=3.6
Requires-Dist: pandas (>=1.0)
Requires-Dist: numpy (>=1.0)
